django_file_picker-0.9.1.dist-info/DESCRIPTION.rst
django_file_picker-0.9.1.dist-info/METADATA
django_file_picker-0.9.1.dist-info/RECORD
django_file_picker-0.9.1.dist-info/WHEEL
django_file_picker-0.9.1.dist-info/metadata.json
django_file_picker-0.9.1.dist-info/top_level.txt
file_picker/__init__.py
file_picker/apps.py
file_picker/forms.py
file_picker/models.py
file_picker/sites.py
file_picker/tests.py
file_picker/views.py
file_picker/widgets.py
file_picker/static/plupload.flash.swf
file_picker/static/css/filepicker.overlay.css
file_picker/static/img/attach.png
file_picker/static/img/close.png
file_picker/static/img/white.png
file_picker/static/js/ajaxupload.js
file_picker/static/js/jquery.filepicker.js
file_picker/static/js/jquery.filepicker.simple.js
file_picker/static/wymeditor/jquery.wymeditor.js
file_picker/static/wymeditor/jquery.wymeditor.min.js
file_picker/static/wymeditor/jquery.wymeditor.pack.js
file_picker/static/wymeditor/iframe/default/lbl-blockquote.png
file_picker/static/wymeditor/iframe/default/lbl-h1.png
file_picker/static/wymeditor/iframe/default/lbl-h2.png
file_picker/static/wymeditor/iframe/default/lbl-h3.png
file_picker/static/wymeditor/iframe/default/lbl-h4.png
file_picker/static/wymeditor/iframe/default/lbl-h5.png
file_picker/static/wymeditor/iframe/default/lbl-h6.png
file_picker/static/wymeditor/iframe/default/lbl-p.png
file_picker/static/wymeditor/iframe/default/lbl-pre.png
file_picker/static/wymeditor/iframe/default/wymiframe.css
file_picker/static/wymeditor/iframe/default/wymiframe.html
file_picker/static/wymeditor/lang/bg.js
file_picker/static/wymeditor/lang/ca.js
file_picker/static/wymeditor/lang/cs.js
file_picker/static/wymeditor/lang/de.js
file_picker/static/wymeditor/lang/en.js
file_picker/static/wymeditor/lang/es.js
file_picker/static/wymeditor/lang/fa.js
file_picker/static/wymeditor/lang/fi.js
file_picker/static/wymeditor/lang/fr.js
file_picker/static/wymeditor/lang/he.js
file_picker/static/wymeditor/lang/hr.js
file_picker/static/wymeditor/lang/hu.js
file_picker/static/wymeditor/lang/it.js
file_picker/static/wymeditor/lang/nb.js
file_picker/static/wymeditor/lang/nl.js
file_picker/static/wymeditor/lang/nn.js
file_picker/static/wymeditor/lang/pl.js
